COPs_analysis_temp/COPsExtension.py
COPs_analysis_temp/__init__.py
COPs_analysis_temp/cops_analysis.py
COPs_Analysis_CCPN-0.0.1.dist-info/LICENSE
COPs_Analysis_CCPN-0.0.1.dist-info/METADATA
COPs_Analysis_CCPN-0.0.1.dist-info/WHEEL
COPs_Analysis_CCPN-0.0.1.dist-info/top_level.txt
COPs_Analysis_CCPN-0.0.1.dist-info/RECORD
