Metadata-Version: 2.1
Name: COPs-Analysis-CCPN
Version: 0.0.1
Summary: A CCPN plugin for analyzing GRADCOPs spectra
Author-email: Harrison Wang <hwang6@fas.harvard.edu>
Project-URL: Homepage, https://github.com/hkwang/COPs_Analysis_CCPN
Project-URL: Bug Tracker, https://github.com/hkwang/COPs_Analysis_CCPN/issues
Classifier: Programming Language :: Python :: 3
Classifier: License :: OSI Approved :: MIT License
Classifier: Operating System :: OS Independent
Requires-Python: >=3.7
License-File: LICENSE
